{
  "title": "Ram Shift Phase 2",
  "author": {
    "name": "Bear, Greg",
    "nation": "美"
  },
  "type": "story",
  "aliases": [],
  "intro": "",
  "prizes": [],
  "publishes": [
    {
      "title": "Ram Shift Phase 2",
      "author": {
        "name": "Bear, Greg",
        "nation": "美"
      },
      "language": null,
      "translator": null,
      "cover": null,
      "date": "2005",
      "publication": "Nature V. 438, No. 7070",
      "publisher": "",
      "type": "periodical",
      "pages": 0,
      "price": null,
      "isbn": "",
      "remark": "",
      "links": [],
      "isfdb": 756941,
      "douban": 0
    },
    {
      "title": "内存2阶移位",
      "author": {
        "name": "格雷格·贝尔",
        "nation": "美"
      },
      "language": "简体中文",
      "translator": {
        "name": "张彤寰",
        "nation": ""
      },
      "cover": null,
      "date": "2009",
      "publication": "《科幻大王》2009年第1期",
      "publisher": "",
      "type": "periodical",
      "pages": 0,
      "price": null,
      "isbn": "",
      "remark": "",
      "links": [],
      "isfdb": 0,
      "douban": 0
    }
  ]
}