{
  "title": "Cassandra's Photographs",
  "author": {
    "name": "Goldstein, Lisa",
    "nation": "美"
  },
  "type": "story",
  "aliases": [],
  "intro": "",
  "prizes": [
    "1987年星云奖最佳短篇提名",
    "1988年雨果奖最佳短篇提名",
    "1988年轨迹奖最佳短篇第7名"
  ],
  "publishes": [
    {
      "title": "Cassandra's Photographs",
      "author": {
        "name": "Goldstein, Lisa",
        "nation": "美"
      },
      "language": null,
      "translator": null,
      "cover": null,
      "date": "1987",
      "publication": "Asimov's, Aug 1987",
      "publisher": "",
      "type": "periodical",
      "pages": 0,
      "price": null,
      "isbn": "",
      "remark": "",
      "links": [],
      "isfdb": 41566,
      "douban": 0
    },
    {
      "title": "卡桑德拉的照片",
      "author": {
        "name": "莉莎·古德斯坦",
        "nation": "美"
      },
      "language": "简体中文",
      "translator": {
        "name": "耿辉",
        "nation": ""
      },
      "cover": null,
      "date": "2007",
      "publication": "《科幻世界》2007年第9期",
      "publisher": "",
      "type": "periodical",
      "pages": 0,
      "price": null,
      "isbn": "",
      "remark": "",
      "links": [],
      "isfdb": 0,
      "douban": 0
    }
  ]
}