{
  "title": "Impact Parameter and Other Quantum Realities",
  "author": {
    "name": "Landis, Geoffrey A.",
    "nation": "美"
  },
  "type": "novel",
  "aliases": [],
  "intro": "",
  "prizes": [
    "2002年轨迹奖最佳选辑第15名"
  ],
  "publishes": [
    {
      "title": "Impact Parameter and Other Quantum Realities",
      "author": {
        "name": "Landis, Geoffrey A.",
        "nation": "美"
      },
      "language": null,
      "translator": null,
      "cover": null,
      "date": "2001",
      "publication": "",
      "publisher": "Golden Gryphon Press",
      "type": "book",
      "pages": 0,
      "price": null,
      "isbn": "",
      "remark": "",
      "links": [],
      "isfdb": 39927,
      "douban": 0
    },
    {
      "title": "冲击参数",
      "author": {
        "name": "杰弗里 A 兰迪斯",
        "nation": "美"
      },
      "language": "简体中文",
      "translator": {
        "name": "陈钢、陈养正",
        "nation": ""
      },
      "cover": null,
      "date": "2008",
      "publication": "",
      "publisher": "重庆出版社",
      "type": "book",
      "pages": 0,
      "price": null,
      "isbn": "",
      "remark": "个人短篇选辑，含16篇",
      "links": [],
      "isfdb": 0,
      "douban": 3105145
    }
  ]
}