{
  "title": "A Feast for Crows",
  "author": {
    "name": "Martin, George R. R.",
    "nation": "美"
  },
  "type": "novel",
  "aliases": [],
  "intro": "",
  "prizes": [
    "2006年雨果奖最佳长篇提名",
    "2006年英国奇幻奖最佳长篇提名",
    "2006年Quill奖最佳科幻奇幻长篇提名",
    "2006年轨迹奖最佳奇幻长篇第2名"
  ],
  "publishes": [
    {
      "title": "A Feast for Crows",
      "author": {
        "name": "Martin, George R. R.",
        "nation": "美"
      },
      "language": null,
      "translator": null,
      "cover": null,
      "date": "2005",
      "publication": "",
      "publisher": "Voyager Books / Bantam Books ",
      "type": "book",
      "pages": 0,
      "price": null,
      "isbn": "",
      "remark": "",
      "links": [],
      "isfdb": 8659,
      "douban": 0
    },
    {
      "title": "冰与火之歌卷四：群鸦的盛宴",
      "author": {
        "name": "乔治·R·R·马丁",
        "nation": "美"
      },
      "language": "简体中文",
      "translator": {
        "name": "屈畅、胡绍晏",
        "nation": ""
      },
      "cover": null,
      "date": "2008",
      "publication": "",
      "publisher": "重庆出版社",
      "type": "book",
      "pages": 0,
      "price": null,
      "isbn": "",
      "remark": "冰与火之歌系列之四",
      "links": [],
      "isfdb": 0,
      "douban": 3210843
    }
  ]
}