{
  "title": "Marooned in Realtime",
  "author": {
    "name": "Vinge, Vernor",
    "nation": "美"
  },
  "type": "novel",
  "aliases": [],
  "intro": "",
  "prizes": [
    "1987年雨果奖最佳长篇提名",
    "1987年轨迹奖最佳科幻长篇第7名",
    "1985年普罗米修斯奖最佳自由主义科幻长篇"
  ],
  "publishes": [
    {
      "title": "Marooned in Realtime",
      "author": {
        "name": "Vinge, Vernor",
        "nation": "美"
      },
      "language": null,
      "translator": null,
      "cover": null,
      "date": "1986",
      "publication": "",
      "publisher": "St. Martin's Press",
      "type": "book",
      "pages": 0,
      "price": null,
      "isbn": "",
      "remark": "",
      "links": [],
      "isfdb": 1567,
      "douban": 0
    },
    {
      "title": "实时放逐",
      "author": {
        "name": "弗诺·文奇",
        "nation": "美"
      },
      "language": "简体中文",
      "translator": {
        "name": "胡绍晏",
        "nation": ""
      },
      "cover": null,
      "date": "2009",
      "publication": "",
      "publisher": "四川科学技术出版社",
      "type": "book",
      "pages": 0,
      "price": null,
      "isbn": "",
      "remark": "",
      "links": [],
      "isfdb": 0,
      "douban": 3607224
    }
  ]
}