{
  "title": "A Hat Full of Sky",
  "author": {
    "name": "Pratchett, Terry",
    "nation": "英"
  },
  "type": "novel",
  "aliases": [],
  "intro": "",
  "prizes": [
    "2005年轨迹奖最佳青年人图书第1名"
  ],
  "publishes": [
    {
      "title": "A Hat Full of Sky",
      "author": {
        "name": "Pratchett, Terry",
        "nation": "英"
      },
      "language": null,
      "translator": null,
      "cover": null,
      "date": "2004",
      "publication": "",
      "publisher": "Doubleday",
      "type": "book",
      "pages": 0,
      "price": null,
      "isbn": "",
      "remark": "",
      "links": [],
      "isfdb": 27027,
      "douban": 0
    },
    {
      "title": "帽子里的天空",
      "author": {
        "name": "特里·普拉切特",
        "nation": "英"
      },
      "language": "简体中文",
      "translator": {
        "name": "林晶",
        "nation": ""
      },
      "cover": null,
      "date": "2005",
      "publication": "",
      "publisher": "人民文学出版社",
      "type": "book",
      "pages": 0,
      "price": null,
      "isbn": "",
      "remark": "",
      "links": [],
      "isfdb": 0,
      "douban": 1844365
    }
  ]
}